Workbook

Sheet Sales Data
A1: Order ID | B1: Order Date | C1: Product | D1: Category | E1: Region | F1: Salesperson | G1: Quantity | H1: Unit Price | I1: Revenue | J1: Discount | K1: Profit
A2: ORD001 | B2: 46025 | C2: Laptop | D2: Technology | E2: North | F2: Rahul | G2: 2 | H2: 55000 | I2: =H2*G2*(1-J2) -> 104500 | J2: 0.05 | K2: =I2*IF(D2="Technology",15%,IF(D2="Furniture",20%,25%)) -> 15675
A3: ORD002 | B3: 46026 | C3: Office Chair | D3: Furniture | E3: South | F3: Priya | G3: 4 | H3: 8500 | I3: =H3*G3*(1-J3) -> 30600 | J3: 0.1 | K3: =I3*IF(D3="Technology",15%,IF(D3="Furniture",20%,25%)) -> 6120
A4: ORD003 | B4: 46027 | C4: Smartphone | D4: Technology | E4: East | F4: Amit | G4: 3 | H4: 32000 | I4: =H4*G4*(1-J4) -> 91200 | J4: 0.05 | K4: =I4*IF(D4="Technology",15%,IF(D4="Furniture",20%,25%)) -> 13680
A5: ORD004 | B5: 46029 | C5: Desk | D5: Furniture | E5: West | F5: Neha | G5: 2 | H5: 12000 | I5: =H5*G5*(1-J5) -> 22080 | J5: 0.08 | K5: =I5*IF(D5="Technology",15%,IF(D5="Furniture",20%,25%)) -> 4416
A6: ORD005 | B6: 46031 | C6: Headphones | D6: Accessories | E6: North | F6: Rahul | G6: 8 | H6: 2500 | I6: =H6*G6*(1-J6) -> 19000 | J6: 0.05 | K6: =I6*IF(D6="Technology",15%,IF(D6="Furniture",20%,25%)) -> 4750
A7: ORD006 | B7: 46033 | C7: Monitor | D7: Technology | E7: South | F7: Priya | G7: 3 | H7: 18000 | I7: =H7*G7*(1-J7) -> 50220 | J7: 0.07 | K7: =I7*IF(D7="Technology",15%,IF(D7="Furniture",20%,25%)) -> 7533
A8: ORD007 | B8: 46034 | C8: Keyboard | D8: Accessories | E8: East | F8: Amit | G8: 10 | H8: 1800 | I8: =H8*G8*(1-J8) -> 17100 | J8: 0.05 | K8: =I8*IF(D8="Technology",15%,IF(D8="Furniture",20%,25%)) -> 4275
A9: ORD008 | B9: 46036 | C9: Printer | D9: Technology | E9: West | F9: Neha | G9: 2 | H9: 14500 | I9: =H9*G9*(1-J9) -> 26100 | J9: 0.1 | K9: =I9*IF(D9="Technology",15%,IF(D9="Furniture",20%,25%)) -> 3915
A10: ORD009 | B10: 46038 | C10: Bookshelf | D10: Furniture | E10: North | F10: Rahul | G10: 3 | H10: 7500 | I10: =H10*G10*(1-J10) -> 21375 | J10: 0.05 | K10: =I10*IF(D10="Technology",15%,IF(D10="Furniture",20%,25%)) -> 4275
A11: ORD010 | B11: 46040 | C11: Mouse | D11: Accessories | E11: South | F11: Priya | G11: 12 | H11: 1200 | I11: =H11*G11*(1-J11) -> 13680 | J11: 0.05 | K11: =I11*IF(D11="Technology",15%,IF(D11="Furniture",20%,25%)) -> 3420
A12: ORD011 | B12: 46042 | C12: Laptop | D12: Technology | E12: East | F12: Amit | G12: 1 | H12: 55000 | I12: =H12*G12*(1-J12) -> 50600 | J12: 0.08 | K12: =I12*IF(D12="Technology",15%,IF(D12="Furniture",20%,25%)) -> 7590
A13: ORD012 | B13: 46044 | C13: Office Chair | D13: Furniture | E13: West | F13: Neha | G13: 5 | H13: 8500 | I13: =H13*G13*(1-J13) -> 38250 | J13: 0.1 | K13: =I13*IF(D13="Technology",15%,IF(D13="Furniture",20%,25%)) -> 7650
... A101: ORD100 | B101: 46233 | C101: Mouse | D101: Accessories | E101: West | F101: Neha | G101: 12 | H101: 1200 | I101: =H101*G101*(1-J101) -> 13680 | J101: 0.05 | K101: =I101*IF(D101="Technology",15%,IF(D101="Furniture",20%,25%)) -> 3420

Sheet Dashboard
A1: SALES & REVENUE ANALYSIS DASHBOARD
J2: Top Product | L2: Top Profit Product
A3: Total Orders | B3: Total Revenue | C3: Total Profit | D3: Total Quantity | E3: Average Order Value | J3: =INDEX(S15:S24,MATCH(MAX(T15:T24),T15:T24,0)) -> Laptop | L3: =INDEX(S15:S24,MATCH(MAX(U15:U24),U15:U24,0)) -> Laptop
A4: =COUNTA('Sales Data'!A2:A101) -> 100 | B4: =SUM('Sales Data'!I2:I101) -> 4080360 | C4: =SUM('Sales Data'!K2:K101) -> 713139.25 | D4: =SUM('Sales Data'!G2:G101) -> 557 | E4: =B4/A4 -> 40803.6 | J4: =MAX(T15:T24) -> 915200 | L4: =MAX(U15:U24) -> 137280
A7: Category | B7: Revenue | D7: Region | E7: Revenue | G7: Salesperson | H7: Revenue | J7: Salesperson | K7: Orders
A8: Technology | B8: =SUMIF('Sales Data'!D2:D101,"Technology",'Sales Data'!I2:I101) -> 2642335 | D8: North | E8: =SUMIF('Sales Data'!E2:E101,D8,'Sales Data'!I2:I101) -> 1209995 | G8: Rahul | H8: =SUMIF('Sales Data'!F2:F101,G8,'Sales Data'!I2:I101) -> 1209995 | J8: Rahul | K8: =COUNTIF('Sales Data'!F2:F101,J8) -> 25
A9: Furniture | B9: =SUMIF('Sales Data'!D3:D102,"Furniture",'Sales Data'!I3:I102) -> 854345 | D9: South | E9: =SUMIF('Sales Data'!E2:E101,D9,'Sales Data'!I2:I101) -> 792980 | G9: Priya | H9: =SUMIF('Sales Data'!F3:F102,G9,'Sales Data'!I3:I102) -> 792980 | J9: Priya | K9: =COUNTIF('Sales Data'!F3:F102,J9) -> 25
A10: Accessories | B10: =SUMIF('Sales Data'!D4:D103,"Accessories",'Sales Data'!I4:I103) -> 583680 | D10: East | E10: =SUMIF('Sales Data'!E4:E103,D10,'Sales Data'!I4:I103) -> 1226170 | G10: Amit | H10: =SUMIF('Sales Data'!F4:F103,G10,'Sales Data'!I4:I103) -> 1226170 | J10: Amit | K10: =COUNTIF('Sales Data'!F4:F103,J10) -> 25
D11: West | E11: =SUMIF('Sales Data'!E5:E104,D11,'Sales Data'!I5:I104) -> 851215 | G11: Neha | H11: =SUMIF('Sales Data'!F5:F104,G11,'Sales Data'!I5:I104) -> 851215 | J11: Neha | K11: =COUNTIF('Sales Data'!F5:F104,J11) -> 25
A14: Month | B14: Revenue | D14: Category | E14: Profit | G14: Region | H14: Profit | J14: Salesperson | K14: Revenue | M14: Category | N14: Revenue | O14: Profit | P14: Profit Margin | S14: Product | T14: Revenue | U14: Profit | V14: Quantity
A15: January | B15: {=SUMPRODUCT((MONTH('Sales Data'!$B$2:$B$101)=ROW()-14)*'Sales Data'!$I$2:$I$101)} -> 593235 | D15: Technology | E15: =SUMIF('Sales Data'!D2:D101,D15,'Sales Data'!K2:K101) -> 396350.25 | G15: North | H15: =SUMIF('Sales Data'!$E:$E,G15,'Sales Data'!$K:$K) -> 212094 | J15: Rahul | K15: 1209995 | M15: Technology | N15: 2642335 | O15: 396350.25 | P15: =O15/N15 -> 0.15 | S15: Laptop | T15: =SUMIF('Sales Data'!$C:$C,S15,'Sales Data'!$I:$I) -> 915200 | U15: =SUMIF('Sales Data'!$C:$C,S15,'Sales Data'!$K:$K) -> 137280 | V15: =SUMIF('Sales Data'!$C:$C,S15,'Sales Data'!$G:$G) -> 18
A16: February | B16: {=SUMPRODUCT((MONTH('Sales Data'!$B$2:$B$101)=ROW()-14)*'Sales Data'!$I$2:$I$101)} -> 578885 | D16: Furniture | E16: =SUMIF('Sales Data'!D3:D102,D16,'Sales Data'!K3:K102) -> 170869 | G16: South | H16: =SUMIF('Sales Data'!$E:$E,G16,'Sales Data'!$K:$K) -> 141877.75 | J16: Priya | K16: 792980 | M16: Furniture | N16: 854345 | O16: 170869 | P16: =O16/N16 -> 0.2 | S16: Office Chair | T16: =SUMIF('Sales Data'!$C:$C,S16,'Sales Data'!$I:$I) -> 332180 | U16: =SUMIF('Sales Data'!$C:$C,S16,'Sales Data'!$K:$K) -> 66436 | V16: =SUMIF('Sales Data'!$C:$C,S16,'Sales Data'!$G:$G) -> 43
A17: March | B17: {=SUMPRODUCT((MONTH('Sales Data'!$B$2:$B$101)=ROW()-14)*'Sales Data'!$I$2:$I$101)} -> 656700 | D17: Accessories | E17: =SUMIF('Sales Data'!D4:D103,D17,'Sales Data'!K4:K103) -> 145920 | G17: East | H17: =SUMIF('Sales Data'!$E:$E,G17,'Sales Data'!$K:$K) -> 209319 | J17: Amit | K17: 1226170 | M17: Accessories | N17: 583680 | O17: 145920 | P17: =O17/N17 -> 0.25 | S17: Smartphone | T17: =SUMIF('Sales Data'!$C:$C,S17,'Sales Data'!$I:$I) -> 843520 | U17: =SUMIF('Sales Data'!$C:$C,S17,'Sales Data'!$K:$K) -> 126528 | V17: =SUMIF('Sales Data'!$C:$C,S17,'Sales Data'!$G:$G) -> 28
A18: April | B18: {=SUMPRODUCT((MONTH('Sales Data'!$B$2:$B$101)=ROW()-14)*'Sales Data'!$I$2:$I$101)} -> 578330 | G18: West | H18: =SUMIF('Sales Data'!$E:$E,G18,'Sales Data'!$K:$K) -> 149848.5 | J18: Neha | K18: 851215 | S18: Desk | T18: =SUMIF('Sales Data'!$C:$C,S18,'Sales Data'!$I:$I) -> 287040 | U18: =SUMIF('Sales Data'!$C:$C,S18,'Sales Data'!$K:$K) -> 57408 | V18: =SUMIF('Sales Data'!$C:$C,S18,'Sales Data'!$G:$G) -> 26
A19: May | B19: {=SUMPRODUCT((MONTH('Sales Data'!$B$2:$B$101)=ROW()-14)*'Sales Data'!$I$2:$I$101)} -> 514810 | S19: Headphones | T19: =SUMIF('Sales Data'!$C:$C,S19,'Sales Data'!$I:$I) -> 199500 | U19: =SUMIF('Sales Data'!$C:$C,S19,'Sales Data'!$K:$K) -> 49875 | V19: =SUMIF('Sales Data'!$C:$C,S19,'Sales Data'!$G:$G) -> 84
A20: June | B20: {=SUMPRODUCT((MONTH('Sales Data'!$B$2:$B$101)=ROW()-14)*'Sales Data'!$I$2:$I$101)} -> 598810 | S20: Monitor | T20: =SUMIF('Sales Data'!$C:$C,S20,'Sales Data'!$I:$I) -> 513720 | U20: =SUMIF('Sales Data'!$C:$C,S20,'Sales Data'!$K:$K) -> 77058 | V20: =SUMIF('Sales Data'!$C:$C,S20,'Sales Data'!$G:$G) -> 31
A21: July | B21: {=SUMPRODUCT((MONTH('Sales Data'!$B$2:$B$101)=ROW()-14)*'Sales Data'!$I$2:$I$101)} -> 559590 | S21: Keyboard | T21: =SUMIF('Sales Data'!$C:$C,S21,'Sales Data'!$I:$I) -> 242820 | U21: =SUMIF('Sales Data'!$C:$C,S21,'Sales Data'!$K:$K) -> 60705 | V21: =SUMIF('Sales Data'!$C:$C,S21,'Sales Data'!$G:$G) -> 142
S22: Printer | T22: =SUMIF('Sales Data'!$C:$C,S22,'Sales Data'!$I:$I) -> 369895 | U22: =SUMIF('Sales Data'!$C:$C,S22,'Sales Data'!$K:$K) -> 55484.25 | V22: =SUMIF('Sales Data'!$C:$C,S22,'Sales Data'!$G:$G) -> 28
S23: Bookshelf | T23: =SUMIF('Sales Data'!$C:$C,S23,'Sales Data'!$I:$I) -> 235125 | U23: =SUMIF('Sales Data'!$C:$C,S23,'Sales Data'!$K:$K) -> 47025 | V23: =SUMIF('Sales Data'!$C:$C,S23,'Sales Data'!$G:$G) -> 33
S24: Mouse | T24: =SUMIF('Sales Data'!$C:$C,S24,'Sales Data'!$I:$I) -> 141360 | U24: =SUMIF('Sales Data'!$C:$C,S24,'Sales Data'!$K:$K) -> 35340 | V24: =SUMIF('Sales Data'!$C:$C,S24,'Sales Data'!$G:$G) -> 124
A92: Key Insights
A93: Technology generated the highest revenue of ₹26,42,335, contributing approximately 65% of total revenue.
A94: Accessories had the highest profit margin at 25%, followed by Furniture at 20% and Technology at 15%.
A95: Laptop was the best-performing product by revenue and profit, generating ₹9,15,200 revenue and ₹1,37,280 profit.
A96: Amit generated the highest revenue of ₹12,26,170 among all salespeople, while each salesperson handled 25 orders.
A97: March recorded the highest monthly revenue at ₹6,56,700, while May recorded the lowest at ₹5,14,810.
